{"nodes": [{"id": "Dan", "name": "Dan", "val": 4}, {"id": "Hebrews", "name": "Hebrews", "val": 6}, {"id": "God", "name": "God", "val": 31}, {"id": "Juda", "name": "Juda", "val": 4}, {"id": "Benjamin", "name": "Benjamin", "val": 1}, {"id": "Joseph", "name": "Joseph", "val": 2}, {"id": "Aser", "name": "Aser", "val": 2}, {"id": "Sephora", "name": "Sephora", "val": 3}, {"id": "Jacob", "name": "Jacob", "val": 5}, {"id": "Levi", "name": "Levi", "val": 4}, {"id": "Isaac", "name": "Isaac", "val": 6}, {"id": "Cetura", "name": "Cetura", "val": 1}, {"id": "Eliezer", "name": "Eliezer", "val": 2}, {"id": "Lord", "name": "Lord", "val": 36}, {"id": "Moyses", "name": "Moyses", "val": 1}, {"id": "Gersam", "name": "Gersam", "val": 2}, {"id": "Abraham", "name": "Abraham", "val": 6}, {"id": "Raguel", "name": "Raguel", "val": 1}, {"id": "bush", "name": "bush", "val": 1}, {"id": "Horeb", "name": "Horeb", "val": 2}, {"id": "Jebusite", "name": "Jebusite", "val": 1}, {"id": "Hethite", "name": "Hethite", "val": 4}, {"id": "Hevite", "name": "Hevite", "val": 1}, {"id": "Amorrhite", "name": "Amorrhite", "val": 1}, {"id": "Immediately Sephora", "name": "Immediately Sephora", "val": 1}, {"id": "Aaron", "name": "Aaron", "val": 26}, {"id": "Jethro", "name": "Jethro", "val": 2}, {"id": "Cast", "name": "Cast", "val": 1}, {"id": "Fulfil", "name": "Fulfil", "val": 1}, {"id": "Pharao", "name": "Pharao", "val": 8}, {"id": "Oziel", "name": "Oziel", "val": 1}, {"id": "Jamuel", "name": "Jamuel", "val": 1}, {"id": "Lobni", "name": "Lobni", "val": 1}, {"id": "Caath", "name": "Caath", "val": 1}, {"id": "Gerson", "name": "Gerson", "val": 1}, {"id": "Aminadab", "name": "Aminadab", "val": 1}, {"id": "Amram", "name": "Amram", "val": 1}, {"id": "Abiu", "name": "Abiu", "val": 3}, {"id": "Sethri", "name": "Sethri", "val": 1}, {"id": "Jod", "name": "Jod", "val": 1}, {"id": "Ahod", "name": "Ahod", "val": 1}, {"id": "Abiasaph", "name": "Abiasaph", "val": 1}, {"id": "Jehovah", "name": "Jehovah", "val": 1}, {"id": "Saul", "name": "Saul", "val": 1}, {"id": "Jachin", "name": "Jachin", "val": 1}, {"id": "Simon", "name": "Simon", "val": 1}, {"id": "Jamin", "name": "Jamin", "val": 1}, {"id": "Musi", "name": "Musi", "val": 1}, {"id": "Shew", "name": "Shew", "val": 1}, {"id": "hitherto thou", "name": "hitherto thou", "val": 1}, {"id": "828", "name": "828", "val": 1}, {"id": "Gessen", "name": "Gessen", "val": 1}, {"id": "Cinifs", "name": "Cinifs", "val": 1}, {"id": "wherein", "name": "wherein", "val": 1}, {"id": "Saviour", "name": "Saviour", "val": 1}, {"id": "Etham", "name": "Etham", "val": 1}, {"id": "Beelsephon", "name": "Beelsephon", "val": 1}, {"id": "Depart", "name": "Depart", "val": 1}, {"id": "Mary", "name": "Mary", "val": 1}, {"id": "Moab", "name": "Moab", "val": 1}, {"id": "Mara", "name": "Mara", "val": 1}, {"id": "Sinai", "name": "Sinai", "val": 2}, {"id": "Manna", "name": "Manna", "val": 1}, {"id": "Hur", "name": "Hur", "val": 2}, {"id": "Amalec", "name": "Amalec", "val": 1}, {"id": "kinsman", "name": "kinsman", "val": 1}, {"id": "Blessed", "name": "Blessed", "val": 1}, {"id": "degrees louder", "name": "degrees louder", "val": 1}, {"id": "Num", "name": "Num", "val": 1}, {"id": "Chron", "name": "Chron", "val": 1}, {"id": "gore", "name": "gore", "val": 1}, {"id": "Jebuzite", "name": "Jebuzite", "val": 1}, {"id": "Nadab", "name": "Nadab", "val": 1}, {"id": "Josue", "name": "Josue", "val": 1}, {"id": "Titles", "name": "Titles", "val": 1}, {"id": "Holy Ghost", "name": "Holy Ghost", "val": 1}, {"id": "whereof southward", "name": "whereof southward", "val": 1}, {"id": "Urim", "name": "Urim", "val": 1}, {"id": "wherein thou", "name": "wherein thou", "val": 1}, {"id": "Thummim", "name": "Thummim", "val": 1}, {"id": "Apoc", "name": "Apoc", "val": 1}, {"id": "gerah", "name": "gerah", "val": 1}, {"id": "Achisamech", "name": "Achisamech", "val": 3}, {"id": "Ooliab", "name": "Ooliab", "val": 3}, {"id": "Uri", "name": "Uri", "val": 3}, {"id": "Nun", "name": "Nun", "val": 1}, {"id": "Mount Sinai", "name": "Mount Sinai", "val": 1}, {"id": "looketh towards", "name": "looketh towards", "val": 1}, {"id": "3828", "name": "3828", "val": 1}, {"id": "4020", "name": "4020", "val": 1}], "links": [{"source": "Dan", "target": "God", "value": 3}, {"source": "Dan", "target": "Juda", "value": 4}, {"source": "God", "target": "Hebrews", "value": 6}, {"source": "Hebrews", "target": "Joseph", "value": 2}, {"source": "Hebrews", "target": "Sephora", "value": 2}, {"source": "Hebrews", "target": "Jacob", "value": 2}, {"source": "Hebrews", "target": "Levi", "value": 2}, {"source": "God", "target": "Juda", "value": 3}, {"source": "God", "target": "Joseph", "value": 2}, {"source": "Aser", "target": "God", "value": 2}, {"source": "God", "target": "Sephora", "value": 3}, {"source": "God", "target": "Jacob", "value": 5}, {"source": "God", "target": "Levi", "value": 4}, {"source": "Aser", "target": "Jacob", "value": 2}, {"source": "Aser", "target": "Levi", "value": 2}, {"source": "Jacob", "target": "Sephora", "value": 2}, {"source": "Levi", "target": "Sephora", "value": 2}, {"source": "Jacob", "target": "Levi", "value": 3}, {"source": "Hebrews", "target": "Lord", "value": 5}, {"source": "God", "target": "Isaac", "value": 6}, {"source": "Isaac", "target": "Lord", "value": 6}, {"source": "Abraham", "target": "Isaac", "value": 6}, {"source": "Isaac", "target": "Jacob", "value": 4}, {"source": "Isaac", "target": "Levi", "value": 3}, {"source": "Eliezer", "target": "God", "value": 2}, {"source": "God", "target": "Lord", "value": 29}, {"source": "Gersam", "target": "God", "value": 2}, {"source": "Abraham", "target": "God", "value": 6}, {"source": "Eliezer", "target": "Sephora", "value": 2}, {"source": "Eliezer", "target": "Lord", "value": 2}, {"source": "Eliezer", "target": "Gersam", "value": 2}, {"source": "Lord", "target": "Sephora", "value": 2}, {"source": "Gersam", "target": "Sephora", "value": 2}, {"source": "Gersam", "target": "Lord", "value": 2}, {"source": "Abraham", "target": "Lord", "value": 6}, {"source": "Jacob", "target": "Lord", "value": 4}, {"source": "Levi", "target": "Lord", "value": 3}, {"source": "Abraham", "target": "Jacob", "value": 4}, {"source": "Abraham", "target": "Levi", "value": 3}, {"source": "Hethite", "target": "Jacob", "value": 2}, {"source": "God", "target": "Horeb", "value": 2}, {"source": "Horeb", "target": "Lord", "value": 2}, {"source": "God", "target": "Hethite", "value": 4}, {"source": "Hethite", "target": "Lord", "value": 4}, {"source": "Abraham", "target": "Hethite", "value": 2}, {"source": "Hethite", "target": "Isaac", "value": 2}, {"source": "Aaron", "target": "God", "value": 21}, {"source": "Aaron", "target": "Lord", "value": 26}, {"source": "Aaron", "target": "Jethro", "value": 2}, {"source": "Aaron", "target": "Abraham", "value": 3}, {"source": "Aaron", "target": "Isaac", "value": 3}, {"source": "God", "target": "Jethro", "value": 2}, {"source": "Jethro", "target": "Lord", "value": 2}, {"source": "God", "target": "Pharao", "value": 8}, {"source": "Aaron", "target": "Pharao", "value": 6}, {"source": "Lord", "target": "Pharao", "value": 8}, {"source": "Aaron", "target": "Abiu", "value": 3}, {"source": "Aaron", "target": "Levi", "value": 2}, {"source": "Abiu", "target": "God", "value": 3}, {"source": "Abiu", "target": "Lord", "value": 3}, {"source": "Aaron", "target": "Hebrews", "value": 3}, {"source": "Hebrews", "target": "Pharao", "value": 3}, {"source": "Aaron", "target": "Sinai", "value": 2}, {"source": "God", "target": "Sinai", "value": 2}, {"source": "Lord", "target": "Sinai", "value": 2}, {"source": "God", "target": "Hur", "value": 2}, {"source": "Aaron", "target": "Hur", "value": 2}, {"source": "Hur", "target": "Lord", "value": 2}, {"source": "Achisamech", "target": "Dan", "value": 3}, {"source": "Achisamech", "target": "Ooliab", "value": 3}, {"source": "Aaron", "target": "Achisamech", "value": 3}, {"source": "Achisamech", "target": "Juda", "value": 3}, {"source": "Achisamech", "target": "God", "value": 2}, {"source": "Achisamech", "target": "Lord", "value": 3}, {"source": "Achisamech", "target": "Uri", "value": 3}, {"source": "Dan", "target": "Ooliab", "value": 3}, {"source": "Aaron", "target": "Dan", "value": 3}, {"source": "Dan", "target": "Lord", "value": 3}, {"source": "Dan", "target": "Uri", "value": 3}, {"source": "Aaron", "target": "Ooliab", "value": 3}, {"source": "Juda", "target": "Ooliab", "value": 3}, {"source": "God", "target": "Ooliab", "value": 2}, {"source": "Lord", "target": "Ooliab", "value": 3}, {"source": "Ooliab", "target": "Uri", "value": 3}, {"source": "Aaron", "target": "Juda", "value": 3}, {"source": "Aaron", "target": "Uri", "value": 3}, {"source": "Juda", "target": "Lord", "value": 3}, {"source": "Juda", "target": "Uri", "value": 3}, {"source": "God", "target": "Uri", "value": 2}, {"source": "Lord", "target": "Uri", "value": 3}]}